fylex/__init__.py
fylex/__main__.py
fylex/fylex.py
fylex-1.2.3.dist-info/licenses/LICENSE.txt
fylex-1.2.3.dist-info/METADATA
fylex-1.2.3.dist-info/WHEEL
fylex-1.2.3.dist-info/entry_points.txt
fylex-1.2.3.dist-info/top_level.txt
fylex-1.2.3.dist-info/RECORD
