Metadata-Version: 2.4
Name: fylex
Version: 1.2.3
Summary: Fylex: A production-ready, high-performance file utility tailored for Linux — with smart copy/move, hashing, filters, undo/redo, and conflict resolution.
Author-email: Sivaprasad Murali <sivaprasad.off@gmail.com>
License: MIT
Project-URL: Homepage, https://github.com/Crystallinecore/fylex
Project-URL: Documentation, https://github.com/Crystallinecore/fylex#readme
Project-URL: Source, https://github.com/Crystallinecore/fylex
Project-URL: Tracker, https://github.com/Crystallinecore/fylex/issues
Project-URL: Releases, https://github.com/Crystallinecore/fylex/releases
Keywords: file,copy,move,cli,linux,utility,xxhash,blake3,filter,conflict,backup,undo,redo,hashing,checksum,deduplication,data-integrity,sysadmin,file-management,sync,devtool,cli-tool,python-tool,smart-copy,smart-move,fylex
Classifier: Development Status :: 5 - Production/Stable
Classifier: Environment :: Console
Classifier: Intended Audience :: Developers
Classifier: Intended Audience :: System Administrators
Classifier: Intended Audience :: End Users/Desktop
Classifier: License :: OSI Approved :: MIT License
Classifier: Operating System :: POSIX :: Linux
Classifier: Programming Language :: Python
Classifier: Programming Language :: Python :: 3
Classifier: Programming Language :: Python :: 3.8
Classifier: Programming Language :: Python :: 3.9
Classifier: Programming Language :: Python :: 3.10
Classifier: Programming Language :: Python :: 3.11
Classifier: Programming Language :: Python :: 3.12
Classifier: Topic :: System :: Filesystems
Classifier: Topic :: Utilities
Classifier: Topic :: Software Development :: Libraries :: Python Modules
Requires-Python: >=3.8
License-File: LICENSE.txt
Requires-Dist: xxhash>=3.0.0
Requires-Dist: blake3>=0.4.0
Dynamic: license-file
